mltools2024/__init__.py
mltools2024/diabetes.py
mltools2024/fibonacci.py
mltools2024/fractionalknapsack.py
mltools2024/huffman.py
mltools2024/main.py
mltools2024/ml-knn-email.py
mltools2024/o-1knapsack.py
mltools2024-0.1.0.dist-info/LICENSE
mltools2024-0.1.0.dist-info/METADATA
mltools2024-0.1.0.dist-info/WHEEL
mltools2024-0.1.0.dist-info/top_level.txt
mltools2024-0.1.0.dist-info/RECORD
